[
    {
        "project_name": "DSCVR",
        "project_logo": "https://internetcomputer.org/img/showcase/dscvr_logo.webp",
        "preferred_icp_hub": "ICP.HUB India",
        "live_on_icp_mainnet": "Yes",
        "money_raised_till_now": "12,00,000",
        "supports_multichain": "Yes",
        "project_elevator_pitch": "https://dscvr.one/",
        "project_tags": [
            "Tech",
            "Blockchain",
            "+ 2 more"
        ],
        "project_area_of_focus": "SocialFi",
        "promotional_video": "https: //www.youtube.com/watch?v=_-MNbRpjSa0",
        "github_link": "https://dscvr.one/",
        "reason_to_join_incubator": "Funding",
        "project_description": "DSCVR is an end-to-end decentralized Web3 social media platform that allows communities to form into groups called Portals. These Portals can be NFT gated",
        "project_cover": "airdrop fungible and non-fungible tokens to their members and much more. DSCVR also allows for tipping posts in a growing number of cryptos",
        "project_team": "supporting ckBTC",
        "token_economics": "a Bitcoin twin living on the Internet Computer.",
        "technical_docs": "",
        "long_term_goals": "",
        "target_market": "",
        "self_rating_of_project": "",
        "user_data": "",
        "mentors_assigned": "",
        "vc_assigned": "",
        "project_twitter": "",
        "project_linkedin": "",
        "project_website": "",
        "project_discord": "",
        "icp_grants": "",
        "investors": "",
        "sns": "",
        "raised_from_other_ecosystem": ""
    },
    {
        "project_name": "OpenChat",
        "project_logo": "https://internetcomputer.org/img/showcase/openchat_logo.webp",
        "preferred_icp_hub": "ICP.Hub Turkey",
        "live_on_icp_mainnet": "Yes",
        "money_raised_till_now": "15,00,000",
        "supports_multichain": "No",
        "project_elevator_pitch": "https://oc.app/",
        "project_tags": [
            "Tech",
            "Blockchain",
            "+ 2 more"
        ],
        "project_area_of_focus": "SocialFi",
        "promotional_video": "https://www.youtube.com/watch?v=qwyOJtNeEUs",
        "github_link": "https://oc.app/",
        "reason_to_join_incubator": "Mentoring",
        "project_description": "OpenChat is a fully decentralized real-time messaging service that is indistinguishable from Web2 chat apps while living 100% on the blockchain. This allows users to send crypto to each other - including Bitcoin - and own a part of OpenChat through CHAT tokens.",
        "project_cover": "",
        "project_team": "",
        "token_economics": "",
        "technical_docs": "",
        "long_term_goals": "",
        "target_market": "",
        "self_rating_of_project": "",
        "user_data": "",
        "mentors_assigned": "",
        "vc_assigned": "",
        "project_twitter": "",
        "project_linkedin": "",
        "project_website": "",
        "project_discord": "",
        "icp_grants": "",
        "investors": "",
        "sns": "",
        "raised_from_other_ecosystem": ""
    },
    {
        "project_name": "Distrikt",
        "project_logo": "https://internetcomputer.org/img/showcase/distrikt_logo.webp",
        "preferred_icp_hub": "ICP.Hub Indonesia",
        "live_on_icp_mainnet": "Yes",
        "money_raised_till_now": "7,50,000",
        "supports_multichain": "No",
        "project_elevator_pitch": "https://distrikt.app/",
        "project_tags": [
            "Tech",
            "Blockchain",
            "+ 2 more"
        ],
        "project_area_of_focus": "SocialFi",
        "promotional_video": "https://distrikt.app/",
        "github_link": "https://distrikt.app/",
        "reason_to_join_incubator": "Incubation",
        "project_description": "Distrikt is a completely decentralized",
        "project_cover": "community-owned Web3 social media platform. Users of the platform will soon be able to vote on upgrades",
        "project_team": "and no user data will ever be mined or sold. Create your account",
        "token_economics": "secured by Internet Identity today.",
        "technical_docs": "",
        "long_term_goals": "",
        "target_market": "",
        "self_rating_of_project": "",
        "user_data": "",
        "mentors_assigned": "",
        "vc_assigned": "",
        "project_twitter": "",
        "project_linkedin": "",
        "project_website": "",
        "project_discord": "",
        "icp_grants": "",
        "investors": "",
        "sns": "",
        "raised_from_other_ecosystem": ""
    },
    {
        "project_name": "Bitfinity EVM",
        "project_logo": "https://internetcomputer.org/img/showcase/bitfinity_evm.png",
        "preferred_icp_hub": "ICP.HUB India",
        "live_on_icp_mainnet": "Yes",
        "money_raised_till_now": "22,00,000",
        "supports_multichain": "No",
        "project_elevator_pitch": "https://bitfinity.network/",
        "project_tags": [
            "Tech",
            "Blockchain",
            "+ 2 more"
        ],
        "project_area_of_focus": "Developer tooling",
        "promotional_video": "https://bitfinity.network/",
        "github_link": "https://bitfinity.network/",
        "reason_to_join_incubator": "Mentoring",
        "project_description": "Bitfinity is the EVM compatibility layer for the IC. Using Bitfinity, you can deploy your Solidity smart contracts to the Internet Computer, taking advantage of its many advantageous DeFi capabilities: HTTP Outcalls, the BTC integration, and more.",
        "project_cover": "",
        "project_team": "see team sheet",
        "token_economics": "https://bitfinity.network/",
        "technical_docs": "https://bitfinity.network/",
        "long_term_goals": "https://bitfinity.network/",
        "target_market": "https://bitfinity.network/",
        "self_rating_of_project": "",
        "user_data": "see team sheet",
        "mentors_assigned": "See mentors sheet",
        "vc_assigned": "see vc sheet",
        "project_twitter": "https://twitter.com/bitfinitynet",
        "project_linkedin": "https://www.linkedin.com/company/icp-hub-italia/",
        "project_website": "https://bitfinity.network/",
        "project_discord": "https://bitfinity.network/",
        "icp_grants": "",
        "investors": "2,00,000",
        "sns": "20,00,000",
        "raised_from_other_ecosystem": ""
    },
    {
        "project_name": "Yumi",
        "project_logo": "https://internetcomputer.org/img/showcase/yumi_logo.webp",
        "preferred_icp_hub": "ICP.Hub LATAM",
        "live_on_icp_mainnet": "Yes",
        "money_raised_till_now": "5,00,000",
        "supports_multichain": "No",
        "project_elevator_pitch": "https://tppkg-ziaaa-aaaal-qatrq-cai.raw.ic0.app/",
        "project_tags": [
            "Tech",
            "Blockchain",
            "+ 2 more"
        ],
        "project_area_of_focus": "NFT",
        "promotional_video": "https://tppkg-ziaaa-aaaal-qatrq-cai.raw.ic0.app/",
        "github_link": "https://tppkg-ziaaa-aaaal-qatrq-cai.raw.ic0.app/",
        "reason_to_join_incubator": "Engaging and building community",
        "project_description": "Yumi is a high-speed",
        "project_cover": "low-cost",
        "project_team": "and fully decentralized NFT marketplace built on the Internet Computer. All digital collectibles available on Yumi are hosted fully on-chain. The minting of NFTs is completely free for creators (no gas fees).",
        "token_economics": "",
        "technical_docs": "",
        "long_term_goals": "",
        "target_market": "",
        "self_rating_of_project": "",
        "user_data": "",
        "mentors_assigned": "",
        "vc_assigned": "",
        "project_twitter": "",
        "project_linkedin": "",
        "project_website": "",
        "project_discord": "",
        "icp_grants": "",
        "investors": "",
        "sns": "",
        "raised_from_other_ecosystem": ""
    },
    {
        "project_name": "Bioniq",
        "project_logo": "https://internetcomputer.org/img/showcase/bioniq-logo.jpeg",
        "preferred_icp_hub": "ICP.Hub LATAM",
        "live_on_icp_mainnet": "Yes",
        "money_raised_till_now": "18,00,000",
        "supports_multichain": "no",
        "project_elevator_pitch": "https://bioniq.io/home/24-hours",
        "project_tags": [
            "Tech",
            "Blockchain",
            "+ 2 more"
        ],
        "project_area_of_focus": "NFT",
        "promotional_video": "https://bioniq.io/home/24-hours",
        "github_link": "https://bioniq.io/home/24-hours",
        "reason_to_join_incubator": "Funding",
        "project_description": "Bioniq is the fastest Ordinals marketplace. Buy",
        "project_cover": "sell",
        "project_team": "and trade with no gas fees",
        "token_economics": "near-instant finality",
        "technical_docs": "and decentralized secure token bridging..",
        "long_term_goals": "",
        "target_market": "",
        "self_rating_of_project": "",
        "user_data": "",
        "mentors_assigned": "",
        "vc_assigned": "",
        "project_twitter": "",
        "project_linkedin": "",
        "project_website": "",
        "project_discord": "",
        "icp_grants": "",
        "investors": "",
        "sns": "",
        "raised_from_other_ecosystem": ""
    }
]